itrsstatsd/__init__.py
itrsstatsd/__version__.py
itrsstatsd/api.py
itrsstatsd/channels.py
itrsstatsd/senders.py
itrsstatsd/severity.py
itrsstatsd/statsd.py
itrsstatsd/units.py
itrsstatsd-2.0.0.dist-info/LICENSE
itrsstatsd-2.0.0.dist-info/METADATA
itrsstatsd-2.0.0.dist-info/WHEEL
itrsstatsd-2.0.0.dist-info/top_level.txt
itrsstatsd-2.0.0.dist-info/RECORD
