Metadata-Version: 2.1
Name: itrsstatsd
Version: 2.0.0
Summary: ITRS StatsD Client
Home-page: https://www.itrsgroup.com
Author: ITRS Group Ltd.
Author-email: support@itrsgroup.com
License: BSD
Keywords: itrs statsd geneos apm
Platform: UNKNOWN
Classifier: Operating System :: OS Independent
Classifier: Programming Language :: Python 
Classifier: Programming Language :: Python :: 3.7
Classifier: Topic :: System :: Monitoring
Classifier: Intended Audience :: Developers
Requires-Python: >=3.7
